streamlit1/__init__.py
streamlit1/streamlit.py
streamlit1-0.1.0.dist-info/METADATA
streamlit1-0.1.0.dist-info/WHEEL
streamlit1-0.1.0.dist-info/RECORD
